{"id":405,"name":"LogLevel","kind":8,"kindString":"Enumeration","flags":{},"children":[{"id":406,"name":"DEBUG","kind":16,"kindString":"Enumeration Member","flags":{},"sources":[{"fileName":"utils/logger.ts","fullFileName":"D:/Web/SolarisUI/src/utils/logger.ts","line":3,"character":4,"url":"https://github.com/SujalChoudhari/SolarisUI/blob/fa34255/src/utils/logger.ts#L3"}],"type":{"type":"literal","value":0},"is":{"declaration":true},"location":{"query":"index.Enum.LogLevel","hash":"DEBUG"},"text":{},"parentId":405},{"id":407,"name":"INFO","kind":16,"kindString":"Enumeration Member","flags":{},"sources":[{"fileName":"utils/logger.ts","fullFileName":"D:/Web/SolarisUI/src/utils/logger.ts","line":4,"character":4,"url":"https://github.com/SujalChoudhari/SolarisUI/blob/fa34255/src/utils/logger.ts#L4"}],"type":{"type":"literal","value":1},"is":{"declaration":true},"location":{"query":"index.Enum.LogLevel","hash":"INFO"},"text":{},"parentId":405},{"id":408,"name":"TIME","kind":16,"kindString":"Enumeration Member","flags":{},"sources":[{"fileName":"utils/logger.ts","fullFileName":"D:/Web/SolarisUI/src/utils/logger.ts","line":5,"character":4,"url":"https://github.com/SujalChoudhari/SolarisUI/blob/fa34255/src/utils/logger.ts#L5"}],"type":{"type":"literal","value":2},"is":{"declaration":true},"location":{"query":"index.Enum.LogLevel","hash":"TIME"},"text":{},"parentId":405},{"id":409,"name":"WARNING","kind":16,"kindString":"Enumeration Member","flags":{},"sources":[{"fileName":"utils/logger.ts","fullFileName":"D:/Web/SolarisUI/src/utils/logger.ts","line":6,"character":4,"url":"https://github.com/SujalChoudhari/SolarisUI/blob/fa34255/src/utils/logger.ts#L6"}],"type":{"type":"literal","value":3},"is":{"declaration":true},"location":{"query":"index.Enum.LogLevel","hash":"WARNING"},"text":{},"parentId":405},{"id":410,"name":"ERROR","kind":16,"kindString":"Enumeration Member","flags":{},"sources":[{"fileName":"utils/logger.ts","fullFileName":"D:/Web/SolarisUI/src/utils/logger.ts","line":7,"character":4,"url":"https://github.com/SujalChoudhari/SolarisUI/blob/fa34255/src/utils/logger.ts#L7"}],"type":{"type":"literal","value":4},"is":{"declaration":true},"location":{"query":"index.Enum.LogLevel","hash":"ERROR"},"text":{},"parentId":405}],"groups":[{"title":"Enumeration Members","children":[406,407,408,409,410]}],"sources":[{"fileName":"utils/logger.ts","fullFileName":"D:/Web/SolarisUI/src/utils/logger.ts","line":2,"character":12,"url":"https://github.com/SujalChoudhari/SolarisUI/blob/fa34255/src/utils/logger.ts#L2"}],"is":{"declaration":true},"location":{"query":"index.Enum.LogLevel","hash":""},"text":{},"parentId":1}
